{"sentences":[{"text":{"content":"Yes she is","begin_offset":0},"sentiment":null}],"tokens":[{"text":{"content":"Yes","begin_offset":0},"part_of_speech":{"tag":"X","aspect":"ASPECT_UNKNOWN","case":"CASE_UNKNOWN","form":"FORM_UNKNOWN","gender":"GENDER_UNKNOWN","mood":"MOOD_UNKNOWN","number":"NUMBER_UNKNOWN","person":"PERSON_UNKNOWN","proper":"PROPER_UNKNOWN","reciprocity":"RECIPROCITY_UNKNOWN","tense":"TENSE_UNKNOWN","voice":"VOICE_UNKNOWN"},"dependency_edge":{"head_token_index":2,"label":"DISCOURSE"},"lemma":"Yes"},{"text":{"content":"she","begin_offset":4},"part_of_speech":{"tag":"PRON","aspect":"ASPECT_UNKNOWN","case":"NOMINATIVE","form":"FORM_UNKNOWN","gender":"FEMININE","mood":"MOOD_UNKNOWN","number":"SINGULAR","person":"THIRD","proper":"PROPER_UNKNOWN","reciprocity":"RECIPROCITY_UNKNOWN","tense":"TENSE_UNKNOWN","voice":"VOICE_UNKNOWN"},"dependency_edge":{"head_token_index":2,"label":"NSUBJ"},"lemma":"she"},{"text":{"content":"is","begin_offset":8},"part_of_speech":{"tag":"VERB","aspect":"ASPECT_UNKNOWN","case":"CASE_UNKNOWN","form":"FORM_UNKNOWN","gender":"GENDER_UNKNOWN","mood":"INDICATIVE","number":"SINGULAR","person":"THIRD","proper":"PROPER_UNKNOWN","reciprocity":"RECIPROCITY_UNKNOWN","tense":"PRESENT","voice":"VOICE_UNKNOWN"},"dependency_edge":{"head_token_index":2,"label":"ROOT"},"lemma":"be"}],"language":"en"}